aws_signv4_mqtt.py
aws_signv4_mqtt-0.2.0.dist-info/LICENSE
aws_signv4_mqtt-0.2.0.dist-info/METADATA
aws_signv4_mqtt-0.2.0.dist-info/WHEEL
aws_signv4_mqtt-0.2.0.dist-info/entry_points.txt
aws_signv4_mqtt-0.2.0.dist-info/top_level.txt
aws_signv4_mqtt-0.2.0.dist-info/RECORD
