Metadata-Version: 2.1
Name: aws-signv4-mqtt
Version: 0.2.0
Summary: Utility to sign urls for aws mqtt
Home-page: https://github.com/pedrohbtp/aws_signv4_mqtt
Author: Pedro Torres
Author-email: 
License: UNKNOWN
Platform: UNKNOWN
Classifier: Programming Language :: Python :: 3
Classifier: License :: OSI Approved :: MIT License
Classifier: Operating System :: OS Independent
